canvas_api_caller/__init__.py
canvas_api_caller-1.0.7.dist-info/METADATA
canvas_api_caller-1.0.7.dist-info/WHEEL
canvas_api_caller-1.0.7.dist-info/top_level.txt
canvas_api_caller-1.0.7.dist-info/RECORD
